Metadata-Version: 1.1
Name: polymath
Version: 0.1.18
Summary: Lightweight and fast implementation of polynomial operations over GF(2).
Home-page: https://github.com/taudor/polymath
Author: Tudor Soroceanu
Author-email: tudor200@zedat.fu-berlin.de
License: UNKNOWN
Download-URL: https://github.com/taudor/polymath/archive/0.1.18.tar.gz
Keywords: polynomials,LFSR,GF(2)
Platform: UNKNOWN
